{
  "job_title": "Senior Clinical Research Associate",
  "career_level": "Senior Level",
  "category": "Clinical Research",
  "job_summary": "A Senior CRA independently manages complex clinical trials, oversees multiple sites, and ensures compliance with protocols and regulations while mentoring junior CRAs.",
  "key_responsibilities": [
    "Conduct and lead monitoring visits (SIV, MV, COV)",
    "Oversee multiple clinical trial sites",
    "Perform advanced Source Data Verification (SDV) and risk assessment",
    "Ensure compliance with Good Clinical Practice",
    "Identify and resolve protocol deviations and site issues",
    "Mentor CRA I/II and junior staff",
    "Prepare high-level monitoring and audit reports"
  ],
  "qualifications": [
    "Bachelor’s/Master’s in Life Sciences / Pharmacy / Nursing",
    "3–6+ years of CRA experience"
  ],
  "skills": [
    "Advanced monitoring expertise",
    "Leadership and mentoring",
    "Risk management"
  ],
  "work_environment": [
    "CROs, pharma companies"
  ],
  "career_path": [
    "Senior CRA → Lead CRA → Clinical Trial Manager"
  ],
  "skills_required": [
    "GCP",
    "GCP compliance",
    "Monitoring",
    "SDV",
    "advanced monitoring expertise",
    "identify and resolve protocol deviations and site issues",
    "leadership and mentoring",
    "mentor cra i/ii and junior staff",
    "oversee multiple clinical trial sites",
    "prepare high-level monitoring and audit reports",
    "risk management",
    "site monitoring"
  ],
  "education_required": [
    "Bachelor",
    "Life Sciences",
    "Master",
    "Nursing"
  ],
  "experience_required": "3–6+ years"
}